{
    "Id": 1464,
    "MSSubClass": 60,
    "MSZoning": "RL",
    "LotFrontage": 78,
    "LotArea": 9978,
    "Street": "Pave",
    "Alley": "NA",
    "LotShape": "IR1",
    "LandContour": "Lvl",
    "Utilities": "AllPub",
    "LotConfig": "Inside",
    "LandSlope": "Gtl",
    "Neighborhood": "Gilbert",
    "Condition1": "Norm",
    "Condition2": "Norm",
    "BldgType": "1Fam",
    "HouseStyle": "2Story",
    "OverallQual": 6,
    "OverallCond": 6,
    "YearBuilt": 1998,
    "YearRemodAdd": 1998,
    "RoofStyle": "Gable",
    "RoofMatl": "CompShg",
    "Exterior1st": "VinylSd",
    "Exterior2nd": "VinylSd",
    "MasVnrType": "BrkFace",
    "MasVnrArea": 20,
    "ExterQual": "TA",
    "ExterCond": "TA",
    "Foundation": "PConc",
    "BsmtQual": "TA",
    "BsmtCond": "TA",
    "BsmtExposure": "No",
    "BsmtFinType1": "GLQ",
    "BsmtFinSF1": 602,
    "BsmtFinType2": "Unf",
    "BsmtFinSF2": 0,
    "BsmtUnfSF": 324,
    "TotalBsmtSF": 926,
    "Heating": "GasA",
    "HeatingQC": "Ex",
    "CentralAir": "Y",
    "Electrical": "SBrkr",
    "stFlrSF": 926,
    "ndFlrSF": 678,
    "LowQualFinSF": 0,
    "GrLivArea": 1604,
    "BsmtFullBath": 0,
    "BsmtHalfBath": 0,
    "FullBath": 2,
    "HalfBath": 1,
    "BedroomAbvGr": 3,
    "KitchenAbvGr": 1,
    "KitchenQual": "Gd",
    "TotRmsAbvGrd": 7,
    "Functional": "Typ",
    "Fireplaces": 1,
    "FireplaceQu": "Gd",
    "GarageType": "Attchd",
    "GarageYrBlt": 1998,
    "GarageFinish": "Fin",
    "GarageCars": 2,
    "GarageArea": 470,
    "GarageQual": "TA",
    "GarageCond": "TA",
    "PavedDrive": "Y",
    "WoodDeckSF": 360,
    "OpenPorchSF": 36,
    "EnclosedPorch": 0,
    "SsnPorch": 0,
    "ScreenPorch": 0,
    "PoolArea": 0,
    "PoolQC": "NA",
    "Fence": "NA",
    "MiscFeature": "NA",
    "MiscVal": 0,
    "MoSold": 6,
    "YrSold": 2010,
    "SaleType": "WD",
    "SaleCondition": "Normal"
}